pydepends/__init__.py
pydepends/depends.py
pydepends-0.1.5.dist-info/METADATA
pydepends-0.1.5.dist-info/WHEEL
pydepends-0.1.5.dist-info/licenses/LICENSE
pydepends-0.1.5.dist-info/RECORD
