Metadata-Version: 2.4
Name: pydepends
Version: 0.1.5
Summary: A python dependency injection system
License: Apache-2.0
License-File: LICENSE
Author: entropy-flux
Author-email: eric.hermosis@gmail.com
Requires-Python: >=3.12,<4.0
Classifier: License :: OSI Approved :: Apache Software License
Classifier: Programming Language :: Python :: 3
Classifier: Programming Language :: Python :: 3.12
Classifier: Programming Language :: Python :: 3.13
Classifier: Programming Language :: Python :: 3.14
